apays/__init__.py
apays/apays_client.py
apays/dependencies.py
apays-0.1.0.dist-info/METADATA
apays-0.1.0.dist-info/WHEEL
apays-0.1.0.dist-info/top_level.txt
apays-0.1.0.dist-info/RECORD
